fast_online_packing/__init__.py
fast_online_packing/helper.py
fast_online_packing/instance_generator.py
fast_online_packing/mwu_max.py
fast_online_packing/online_solver.py
fast_online_packing/packing_problem.py
fast_online_packing/offline_solvers/__init__.py
fast_online_packing/offline_solvers/base_solver.py
fast_online_packing/offline_solvers/google_knapsack_solver.py
fast_online_packing/offline_solvers/python_mip_solver.py
fast_online_packing-1.0.0.dist-info/LICENSE.txt
fast_online_packing-1.0.0.dist-info/METADATA
fast_online_packing-1.0.0.dist-info/WHEEL
fast_online_packing-1.0.0.dist-info/top_level.txt
fast_online_packing-1.0.0.dist-info/RECORD
