Metadata-Version: 2.1
Name: fast-online-packing
Version: 1.0.0
Summary: A fast algorithm for online packing.
Home-page: https://github.com/dbeyda/fast-online-packing/
Author: David Beyda
Author-email: dbeyda@poli.ufrj.br
License: UNKNOWN
Project-URL: Documentation, https://dbeyda.github.io/fast-online-packing/
Platform: UNKNOWN
Classifier: Programming Language :: Python :: 3
Classifier: License :: OSI Approved :: MIT License
Classifier: Operating System :: OS Independent
Requires-Python: >=3.9
License-File: LICENSE.txt
Requires-Dist: mip (>=1.13.0)
Requires-Dist: ortools (>=8.2.8)
